{
    "config": {
        "version": "1.10",
        "formRef": "elForm",
        "formModel": "form",
        "rules": "rules",
        "size": "medium",
        "labelPosition": "right",
        "labelWidth": 80,
        "formRules": "rules",
        "gutter": 15,
        "disabled": false,
        "dynamicTableAllowed": true
    },
    "list": [
        {
            "id": "fd_1660826944105",
            "_id": "fd_1660826944105",
            "compType": "input",
            "ele": "el-input",
            "compName": "单行文本",
            "compIcon": "input",
            "viewType": "text",
            "config": true,
            "showLabel": true,
            "label": "aaa",
            "labelWidth": 80,
            "placeholder": "请输入文本",
            "required": false,
            "maxLength": 50,
            "gutter": 15,
            "span": 12,
            "width": "100%",
            "clearable": true,
            "disabled": false,
            "readonly": false,
            "status": "normal",
            "prefix-icon": "",
            "suffix-icon": "",
            "value": "大幅度反对法",
            "rules": [],
            "rulesType": "default",
            "prepend": "",
            "append": "",
            "layout": "colItem"
        },
        {
            "id": "fd_1660827192575",
            "_id": "fd_1660827192575",
            "compType": "date",
            "ele": "el-date-picker",
            "compName": "日期",
            "compIcon": "date",
            "viewType": "text",
            "config": true,
            "showLabel": true,
            "label": "日期",
            "labelWidth": 80,
            "placeholder": "请选择",
            "required": false,
            "maxLength": 50,
            "gutter": 15,
            "span": 24,
            "clearable": true,
            "disabled": false,
            "readonly": false,
            "value": "2022-08-11",
            "rules": [],
            "type": "date",
            "format": "yyyy-MM-dd",
            "value-format": "yyyy-MM-dd",
            "range-separator": "-",
            "start-placeholder": "开始日期",
            "end-placeholder": "结束日期",
            "layout": "colItem"
        },
        {
            "id": "fd_1660828463262",
            "_id": "fd_1660828463262",
            "compType": "dynamicTable",
            "ele": "dynamic-table",
            "compName": "动态表格",
            "layout": "dynamicItem",
            "compIcon": "table",
            "labelWidth": 0,
            "showLabel": false,
            "config": true,
            "buttonAdd": true,
            "buttonDel": true,
            "showIndex": true,
            "visible": true,
            "multiCheck": false,
            "show-summary": false,
            "sum-text": "合计",
            "summary-text": "元",
            "columns": [
                {
                    "id": "fd_1660828471808",
                    "_id": "fd_1660828471808",
                    "compType": "input",
                    "ele": "el-input",
                    "compName": "单行文本",
                    "compIcon": "input",
                    "viewType": "text",
                    "config": true,
                    "showLabel": true,
                    "label": "单行文本",
                    "labelWidth": 80,
                    "placeholder": "请输入文本",
                    "required": false,
                    "maxLength": 50,
                    "gutter": 15,
                    "span": 24,
                    "width": "100%",
                    "clearable": true,
                    "disabled": false,
                    "readonly": false,
                    "status": "normal",
                    "prefix-icon": "",
                    "suffix-icon": "",
                    "value": "ssss",
                    "rules": [],
                    "rulesType": "default",
                    "prepend": "",
                    "append": "",
                    "layout": "colItem"
                },
                {
                    "id": "fd_1660828477264",
                    "_id": "fd_1660828477264",
                    "compType": "input",
                    "ele": "el-input",
                    "compName": "单行文本",
                    "compIcon": "input",
                    "viewType": "text",
                    "config": true,
                    "showLabel": true,
                    "label": "单行文本",
                    "labelWidth": 80,
                    "placeholder": "请输入文本",
                    "required": false,
                    "maxLength": 50,
                    "gutter": 15,
                    "span": 24,
                    "width": "100%",
                    "clearable": true,
                    "disabled": false,
                    "readonly": false,
                    "status": "normal",
                    "prefix-icon": "",
                    "suffix-icon": "",
                    "value": "",
                    "rules": [],
                    "rulesType": "default",
                    "prepend": "",
                    "append": "",
                    "layout": "colItem"
                },
                {
                    "id": "fd_1660828478937",
                    "_id": "fd_1660828478937",
                    "compType": "input",
                    "ele": "el-input",
                    "compName": "单行文本",
                    "compIcon": "input",
                    "viewType": "text",
                    "config": true,
                    "showLabel": true,
                    "label": "单行文本",
                    "labelWidth": 80,
                    "placeholder": "请输入文本",
                    "required": false,
                    "maxLength": 50,
                    "gutter": 15,
                    "span": 24,
                    "width": "100%",
                    "clearable": true,
                    "disabled": false,
                    "readonly": false,
                    "status": "normal",
                    "prefix-icon": "",
                    "suffix-icon": "",
                    "value": "",
                    "rules": [],
                    "rulesType": "default",
                    "prepend": "",
                    "append": "",
                    "layout": "colItem"
                }
            ]
        },
        {
            "id": "fd_1660828516799",
            "_id": "fd_1660828516799",
            "compType": "editor",
            "ele": "fancy-editor",
            "compName": "编辑器",
            "compIcon": "editor",
            "viewType": "html",
            "config": true,
            "form": true,
            "showLabel": true,
            "labelWidth": 80,
            "label": "文本编辑器",
            "value": "",
            "required": false,
            "validateMaxText": false,
            "max": 2000,
            "customRules": [],
            "layout": "colItem"
        }
    ]
}